hangmanultimate/__init__.py
hangmanultimate/__main__.py
hangmanultimate/data.py
hangmanultimate/hangman.py
hangman_ultimate-1.0.2.dist-info/LICENSE
hangman_ultimate-1.0.2.dist-info/METADATA
hangman_ultimate-1.0.2.dist-info/WHEEL
hangman_ultimate-1.0.2.dist-info/entry_points.txt
hangman_ultimate-1.0.2.dist-info/top_level.txt
hangman_ultimate-1.0.2.dist-info/RECORD
