Metadata-Version: 2.1
Name: hangman-ultimate
Version: 1.0.2
Summary: A Game of Hangman
Home-page: https://github.com/devarshi16/HangMan
Author: devarshi16
Author-email: devershigpt6@gmail.com
License: UNKNOWN
Keywords: hangman hangman-game python-tutorial hangman-python terminal-game game pokemon
Platform: UNKNOWN
Classifier: Development Status :: 4 - Beta
Classifier: Programming Language :: Python :: 3.5
Classifier: License :: OSI Approved :: MIT License
Classifier: Operating System :: Unix
Requires-Python: >=3.5
Requires-Dist: readchar (>=2.0.1)
Requires-Dist: termcolor (>=1.1.0)
